packyak/__init__.py
packyak/asset/asset.py
packyak/asset/manifest.py
packyak/asset/namespace.py
packyak/asset/partition_key.py
packyak/asset/source.py
packyak/cli/__init__.py
packyak/cli/__main__.py
packyak/cli/cli.py
packyak/cli/clusters.py
packyak/cli/instances.py
packyak/cli/list.py
packyak/cli/logs.py
packyak/cli/materialize.py
packyak/cli/new.py
packyak/cli/node_type.py
packyak/cli/run.py
packyak/cli/ssh.py
packyak/cli/synth.py
packyak/duration.py
packyak/py.typed
packyak/resource.py
packyak/runtime/binding.py
packyak/runtime/cluster.py
packyak/runtime/function.py
packyak/runtime/integration.py
packyak/runtime/job.py
packyak/runtime/pool.py
packyak/runtime/runnable.py
packyak/scheduling/cron.py
packyak/scheduling/every.py
packyak/spark/__init__.py
packyak/spark/session.py
packyak/spec.py
packyak/storage/bucket.py
packyak/storage/folder.py
packyak/streaming/queue.py
packyak/synth/__init__.py
packyak/synth/__main__.py
packyak/synth/analyze.py
packyak/synth/call.py
packyak/synth/file_utils.py
packyak/synth/loaded_module.py
packyak/synth/synth.py
packyak/util/emr.py
packyak/util/fqn.py
packyak/util/git.py
packyak/util/memoize.py
packyak/util/typed_resource.py
packyak/web/streamlit-site.py
packyak-0.4.22.dist-info/METADATA
packyak-0.4.22.dist-info/WHEEL
packyak-0.4.22.dist-info/entry_points.txt
packyak-0.4.22.dist-info/RECORD
