Metadata-Version: 2.1
Name: packyak
Version: 0.4.22
Summary: Infrastructure for AI applications and machine learning pipelines
Author: sam
Author-email: sam@eventual.ai
Requires-Python: >=3.10,<4.0
Classifier: Programming Language :: Python :: 3
Classifier: Programming Language :: Python :: 3.10
Classifier: Programming Language :: Python :: 3.11
Classifier: Programming Language :: Python :: 3.12
Requires-Dist: aioboto3 (>=12.1.0,<13.0.0)
Requires-Dist: aiobotocore[boto3] (==2.8.0)
Requires-Dist: aiofiles (>=23.2.1,<24.0.0)
Requires-Dist: asyncclick (>=8.1.7.1,<9.0.0.0)
Requires-Dist: aws-lambda-typing (>=2.18.0,<3.0.0)
Requires-Dist: boto3-stubs[emr,essential,ssm,sts] (>=1.34.15,<2.0.0)
Requires-Dist: click (>=8.1.7,<9.0.0)
Requires-Dist: findspark (>=2.0.1,<3.0.0)
Requires-Dist: pandas (>2)
Requires-Dist: pandas-stubs (>2)
Requires-Dist: pandera
Requires-Dist: pydantic (>=2.5.3,<3.0.0)
Requires-Dist: pyspark[pandas-on-spark] (>=3.5.0,<4.0.0)
Requires-Dist: tabulate (>=0.9.0,<0.10.0)
Requires-Dist: types-aiobotocore[emr,essential] (>=2.9.0,<3.0.0)
Requires-Dist: types-boto3 (>=1.0.2,<2.0.0)
